bric-sphinx-bootstrap/__init__.py
bric_sphinx_bootstrap/__init__.py
sphinx-bootstrap/__init__.py
bric_sphinx_bootstrap-0.0.4.dist-info/METADATA
bric_sphinx_bootstrap-0.0.4.dist-info/WHEEL
bric_sphinx_bootstrap-0.0.4.dist-info/top_level.txt
bric_sphinx_bootstrap-0.0.4.dist-info/RECORD
