Metadata-Version: 2.1
Name: bric-sphinx-bootstrap
Version: 0.0.4
Summary: Sphinx roles for Bootstrap elelments.
Home-page: UNKNOWN
Author: Brian Carlsen
Author-email: carlsen.bri@gmail.com
License: UNKNOWN
Project-URL: Source Code, https://github.com/bicarlsen/sphinx-bootstrap
Project-URL: Bug Tracker, https://github.com/bicarlsen/sphinx-bootstrap/issues
Keywords: sphinx,rst,restructured text,bootstrap
Platform: UNKNOWN
Classifier: Programming Language :: Python :: 3
Classifier: License :: OSI Approved :: MIT License
Classifier: Operating System :: OS Independent
Classifier: Development Status :: 3 - Alpha
Requires-Dist: docutils
Requires-Dist: Sphinx
